tiktok_account_checker/__init__.py
tiktok_account_checker/tiktok_checker.py
tiktok_account_checker-0.1.0.dist-info/METADATA
tiktok_account_checker-0.1.0.dist-info/WHEEL
tiktok_account_checker-0.1.0.dist-info/top_level.txt
tiktok_account_checker-0.1.0.dist-info/RECORD
