Metadata-Version: 2.4
Name: tiktok_account_checker
Version: 0.1.0
Summary: A Python library to check TikTok account binding status and supporter level.
Author: JACK
Classifier: Programming Language :: Python :: 3
Classifier: License :: OSI Approved :: MIT License
Classifier: Operating System :: OS Independent
Requires-Python: >=3.6
Requires-Dist: requests
Requires-Dist: SignerPy
Requires-Dist: MedoSigner
Dynamic: author
Dynamic: classifier
Dynamic: description
Dynamic: description-content-type
Dynamic: requires-dist
Dynamic: requires-python
Dynamic: summary
